eks_pv_encrypter/aws_utils.py
eks_pv_encrypter/cli.py
eks_pv_encrypter/k8s_utils.py
eks_pv_encrypter/logger.py
eks_pv_encrypter/main.py
eks_pv_encrypter-0.3.0.dist-info/LICENSE
eks_pv_encrypter-0.3.0.dist-info/entry_points.txt
eks_pv_encrypter-0.3.0.dist-info/WHEEL
eks_pv_encrypter-0.3.0.dist-info/METADATA
eks_pv_encrypter-0.3.0.dist-info/RECORD
