Metadata-Version: 2.1
Name: eks-pv-encrypter
Version: 0.3.0
Summary: A simple tool to encrypt the EBS volumes linked to your EKS Persistent Volumes.
Author: Vishnu Deva
Author-email: vishnu.d@madstreetden.com
Requires-Python: >=3.9,<3.10
Classifier: Programming Language :: Python :: 3
Classifier: Programming Language :: Python :: 3.9
Requires-Dist: black[jupyter] (>=22.12.0,<23.0.0)
Requires-Dist: boto3 (>=1.26.41,<2.0.0)
Requires-Dist: fire (>=0.5.0,<0.6.0)
Requires-Dist: ipykernel (>=6.19.4,<7.0.0)
Requires-Dist: kubernetes (>=25.3.0,<26.0.0)
Requires-Dist: rich (>=13.0.0,<14.0.0)
Project-URL: repository, https://github.com/VishDev12/eks-pv-encrypter
